{
  "sections": {
    "006c7455-99df-46f7-bd41-b2d491e4f640": {
      "type": "image-banner",
      "settings": {
        "image": "shopify:\/\/shop_images\/103023_SITE_HP_EA_nonmember_Desktop_staticNoCTA_1944x.progressive_9daa8a26-2750-4dc1-9dcb-fcd76e03ce2f.webp",
        "image_overlay_opacity": 0,
        "image_height": "adapt",
        "desktop_content_position": "middle-center",
        "show_text_box": true,
        "desktop_content_alignment": "left",
        "color_scheme": "",
        "image_behavior": "ambient",
        "mobile_content_alignment": "center",
        "stack_images_on_mobile": true,
        "show_text_below": true
      }
    },
    "featured_collection": {
      "type": "featured-collection",
      "settings": {
        "title": "Featured products",
        "heading_size": "h2",
        "description": "",
        "show_description": false,
        "description_style": "body",
        "collection": "all",
        "products_to_show": 8,
        "columns_desktop": 4,
        "full_width": false,
        "show_view_all": true,
        "view_all_style": "solid",
        "enable_desktop_slider": false,
        "color_scheme": "background-1",
        "image_ratio": "adapt",
        "image_shape": "default",
        "show_secondary_image": true,
        "show_vendor": false,
        "show_rating": false,
        "enable_quick_add": false,
        "columns_mobile": "2",
        "swipe_on_mobile": false,
        "padding_top": 44,
        "padding_bottom": 36
      }
    },
    "4bb0670a-0d0c-406c-9fe4-b365b5403cfa": {
      "type": "collage",
      "blocks": {
        "template--16906406363377__4bb0670a-0d0c-406c-9fe4-b365b5403cfa-product-1": {
          "type": "product",
          "settings": {
            "product": "",
            "second_image": false
          }
        },
        "template--16906406363377__4bb0670a-0d0c-406c-9fe4-b365b5403cfa-collection-1": {
          "type": "collection",
          "settings": {
            "collection": ""
          }
        }
      },
      "block_order": [
        "template--16906406363377__4bb0670a-0d0c-406c-9fe4-b365b5403cfa-product-1",
        "template--16906406363377__4bb0670a-0d0c-406c-9fe4-b365b5403cfa-collection-1"
      ],
      "settings": {
        "heading": "Multimedia collage",
        "heading_size": "h1",
        "desktop_layout": "right",
        "mobile_layout": "column",
        "card_styles": "none",
        "color_scheme": "",
        "padding_top": 36,
        "padding_bottom": 36
      }
    },
    "101a9a14-6115-4e4e-bb7c-51b4ab7577be": {
      "type": "collection-list",
      "blocks": {
        "template--16906406363377__101a9a14-6115-4e4e-bb7c-51b4ab7577be-featured_collection-1": {
          "type": "featured_collection",
          "settings": {
            "collection": "best-sellers"
          }
        },
        "template--16906406363377__101a9a14-6115-4e4e-bb7c-51b4ab7577be-featured_collection-2": {
          "type": "featured_collection",
          "settings": {
            "collection": "leggings"
          }
        },
        "template--16906406363377__101a9a14-6115-4e4e-bb7c-51b4ab7577be-featured_collection-3": {
          "type": "featured_collection",
          "settings": {
            "collection": "new-arrivals"
          }
        }
      },
      "block_order": [
        "template--16906406363377__101a9a14-6115-4e4e-bb7c-51b4ab7577be-featured_collection-1",
        "template--16906406363377__101a9a14-6115-4e4e-bb7c-51b4ab7577be-featured_collection-2",
        "template--16906406363377__101a9a14-6115-4e4e-bb7c-51b4ab7577be-featured_collection-3"
      ],
      "custom_css": [
        "h2 {text-transform: uppercase; margin-left: 32rem; font-family: \"arquitecta\", Arial, sans-serif; font-size: 3rem; text-align: center;}"
      ],
      "settings": {
        "title": "<strong>What are you looking for?<\/strong>",
        "heading_size": "h1",
        "image_ratio": "square",
        "columns_desktop": 3,
        "color_scheme": "",
        "show_view_all": false,
        "columns_mobile": "1",
        "swipe_on_mobile": false,
        "padding_top": 36,
        "padding_bottom": 36
      }
    },
    "f9c045f4-8f27-4b09-8e02-f944e28c6a12": {
      "type": "image-banner",
      "blocks": {
        "template--16906406363377__f9c045f4-8f27-4b09-8e02-f944e28c6a12-buttons-1": {
          "type": "buttons",
          "settings": {
            "button_label_1": "EXPLORE ALO",
            "button_link_1": "",
            "button_style_secondary_1": false,
            "button_label_2": "Button label",
            "button_link_2": "",
            "button_style_secondary_2": false
          }
        }
      },
      "block_order": [
        "template--16906406363377__f9c045f4-8f27-4b09-8e02-f944e28c6a12-buttons-1"
      ],
      "custom_css": [
        "button {display: none;}"
      ],
      "settings": {
        "image": "shopify:\/\/shop_images\/08.31.23_NewToAlo_HP_Desktop_copy_1_1944x.progressive_488f26ac-058e-40ff-89d3-cd5f5bc8cef2.webp",
        "image_overlay_opacity": 0,
        "image_height": "medium",
        "desktop_content_position": "bottom-center",
        "show_text_box": true,
        "desktop_content_alignment": "center",
        "color_scheme": "",
        "image_behavior": "none",
        "mobile_content_alignment": "center",
        "stack_images_on_mobile": true,
        "show_text_below": true
      }
    }
  },
  "order": [
    "006c7455-99df-46f7-bd41-b2d491e4f640",
    "featured_collection",
    "4bb0670a-0d0c-406c-9fe4-b365b5403cfa",
    "101a9a14-6115-4e4e-bb7c-51b4ab7577be",
    "f9c045f4-8f27-4b09-8e02-f944e28c6a12"
  ]
}
